davidkhala/utils/geo.py
davidkhala/utils/sql.py
davidkhala/utils/build/__init__.py
davidkhala/utils/http_request/__init__.py
davidkhala/utils/http_request/proxy.py
davidkhala/utils/http_request/stream.py
davidkhala/utils/poetry/__init__.py
davidkhala/utils/poetry/cli.py
davidkhala/utils/syntax/__init__.py
davidkhala/utils/syntax/compat.py
davidkhala/utils/syntax/env.py
davidkhala/utils/syntax/format.py
davidkhala/utils/syntax/fs.py
davidkhala/utils/syntax/interface.py
davidkhala/utils/syntax/js.py
davidkhala/utils/syntax/log.py
davidkhala/utils/syntax/network.py
davidkhala/utils/syntax/path.py
davidkhala/utils/syntax/time.py
davidkhala/utils/syntax/typing.py
davidkhala_utils-0.7.1.dist-info/METADATA
davidkhala_utils-0.7.1.dist-info/WHEEL
davidkhala_utils-0.7.1.dist-info/entry_points.txt
davidkhala_utils-0.7.1.dist-info/licenses/LICENSE
davidkhala_utils-0.7.1.dist-info/RECORD
