Metadata-Version: 2.4
Name: davidkhala.utils
Version: 0.7.1
Summary: @davidkhala/python-utils
Author-email: David Liu <david-khala@hotmail.com>
License-File: LICENSE
Requires-Python: >=3.10
Provides-Extra: build
Requires-Dist: pyinstaller; (python_version < '3.14') and extra == 'build'
Provides-Extra: geo
Requires-Dist: numpy; extra == 'geo'
Provides-Extra: http-request
Requires-Dist: requests; extra == 'http-request'
Provides-Extra: poetry
Requires-Dist: python-dotenv; extra == 'poetry'
Provides-Extra: sql
Requires-Dist: sqlparse; extra == 'sql'
